slopping/__init__.py
slopping/__main__.py
slopping/slopping.py
slopping-1.0.0.dist-info/METADATA
slopping-1.0.0.dist-info/WHEEL
slopping-1.0.0.dist-info/entry_points.txt
slopping-1.0.0.dist-info/licenses/LICENSE
slopping-1.0.0.dist-info/RECORD
