Metadata-Version: 2.1
Name: slopping
Version: 1.0.0
Summary: Script to feed cropping coordinates to ffmpeg (or a PIL.Image crop)
Project-URL: Homepage, https://github.com/4ndrs/slopping
Project-URL: Bug Tracker, https://github.com/4ndrs/slopping/issues
Author-email: 4ndrs <andres.degozaru@gmail.com>
License: MIT License
Classifier: License :: OSI Approved :: MIT License
Classifier: Operating System :: POSIX :: Linux
Classifier: Programming Language :: Python :: 3
Classifier: Topic :: Software Development :: Libraries :: Python Modules
Requires-Python: >=3.10
